libimagequant_integrations/PIL.py
libimagequant_integrations/PyQt5.py
libimagequant_integrations/PyQt6.py
libimagequant_integrations/PySide2.py
libimagequant_integrations/PySide6.py
libimagequant_integrations/_Qt.py
libimagequant_integrations/__init__.py
libimagequant_integrations/png.py
libimagequant_integrations/skimage.py
libimagequant_integrations-1.1.1.dist-info/LICENSE
libimagequant_integrations-1.1.1.dist-info/METADATA
libimagequant_integrations-1.1.1.dist-info/WHEEL
libimagequant_integrations-1.1.1.dist-info/top_level.txt
libimagequant_integrations-1.1.1.dist-info/RECORD
