Metadata-Version: 2.1
Name: libimagequant-integrations
Version: 1.1.1
Summary: UNKNOWN
Home-page: https://github.com/RoadrunnerWMC/libimagequant-python-integrations
Author: RoadrunnerWMC
Author-email: roadrunnerwmc@gmail.com
License: UNKNOWN
Platform: UNKNOWN
Classifier: Programming Language :: Python :: 3.5
Classifier: Programming Language :: Python :: 3.6
Classifier: Programming Language :: Python :: 3.7
Classifier: Programming Language :: Python :: 3.8
Classifier: Programming Language :: Python :: 3.9
Classifier: Programming Language :: Python :: Implementation :: PyPy
Classifier: Topic :: Multimedia :: Graphics
Classifier: License :: OSI Approved :: GNU General Public License v3 or later (GPLv3+)
Requires-Python: >=3.5
Requires-Dist: libimagequant
